yaml_patch/__init__.py
yaml_patch/cli.py
yaml_patch/patch.py
yaml_patch-1.1.0.dist-info/entry_points.txt
yaml_patch-1.1.0.dist-info/LICENSE
yaml_patch-1.1.0.dist-info/WHEEL
yaml_patch-1.1.0.dist-info/METADATA
yaml_patch-1.1.0.dist-info/RECORD
