Metadata-Version: 2.1
Name: yaml-patch
Version: 1.1.0
Summary: Patch yaml strings
Home-page: https://github.com/campos-ddc/yaml-patch
License: MIT
Author: Diogo de Campos
Author-email: campos.ddc@gmail.com
Requires-Python: >=3.7,<4.0
Classifier: License :: OSI Approved :: MIT License
Classifier: Programming Language :: Python :: 3
Classifier: Programming Language :: Python :: 3.7
Classifier: Programming Language :: Python :: 3.8
Classifier: Programming Language :: Python :: 3.9
Classifier: Programming Language :: Python :: 3.10
Requires-Dist: click (>=8.0.1,<9.0.0)
Requires-Dist: ruamel.yaml (>=0.17.11,<0.18.0)
